lcd_driver.v
`timescale 1ns/1ps
module lcd_driver (
    input  wire [3:0] alarm_time,
    input  wire [3:0] current_time,
    input  wire       show_alarm,
    input  wire       show_new_time,
    input  wire [3:0] key,
    output reg  [7:0] display_time,
    output reg        sound_alarm
);

    reg [3:0] display_value;

    parameter ZERO  = 8'h30;
    parameter ONE   = 8'h31;
    parameter TWO   = 8'h32;
    parameter THREE = 8'h33;
    parameter FOUR  = 8'h34;
    parameter FIVE  = 8'h35;
    parameter SIX   = 8'h36;
    parameter SEVEN = 8'h37;
    parameter EIGHT = 8'h38;
    parameter NINE  = 8'h39;
    parameter ERROR = 8'h3A;

    always @(*) begin
        if (show_alarm)
            display_value = alarm_time;
        else if (show_new_time)
            display_value = key;
        else
            display_value = current_time;

        sound_alarm = (current_time == alarm_time);
    end

    always @(*) begin
        case (display_value)
            4'd0: display_time = ZERO;
            4'd1: display_time = ONE;
            4'd2: display_time = TWO;
            4'd3: display_time = THREE;
            4'd4: display_time = FOUR;
            4'd5: display_time = FIVE;
            4'd6: display_time = SIX;
            4'd7: display_time = SEVEN;
            4'd8: display_time = EIGHT;
            4'd9: display_time = NINE;
            default: display_time = ERROR;
        endcase
    end
endmodule

lcd_driver_4.v
`timescale 1ns/1ps
module lcd_driver_4 (
    input  wire [3:0] alarm_time_ms_hr,
    input  wire [3:0] alarm_time_ls_hr,
    input  wire [3:0] alarm_time_ms_min,
    input  wire [3:0] alarm_time_ls_min,
    input  wire [3:0] current_time_ms_hr,
    input  wire [3:0] current_time_ls_hr,
    input  wire [3:0] current_time_ms_min,
    input  wire [3:0] current_time_ls_min,
    input  wire [3:0] key_ms_hr,
    input  wire [3:0] key_ls_hr,
    input  wire [3:0] key_ms_min,
    input  wire [3:0] key_ls_min,
    input  wire       show_a,
    input  wire       show_current_time,
    output wire [7:0] display_ms_hr,
    output wire [7:0] display_ls_hr,
    output wire [7:0] display_ms_min,
    output wire [7:0] display_ls_min,
    output wire       sound_a
);

    wire sound_alarm1, sound_alarm2, sound_alarm3, sound_alarm4;

    lcd_driver MS_HR (
        .alarm_time(alarm_time_ms_hr),
        .current_time(current_time_ms_hr),
        .show_alarm(show_a),
        .show_new_time(show_current_time),
        .key(key_ms_hr),
        .display_time(display_ms_hr),
        .sound_alarm(sound_alarm1)
    );

    lcd_driver LS_HR (
        .alarm_time(alarm_time_ls_hr),
        .current_time(current_time_ls_hr),
        .show_alarm(show_a),
        .show_new_time(show_current_time),
        .key(key_ls_hr),
        .display_time(display_ls_hr),
        .sound_alarm(sound_alarm2)
    );

    lcd_driver MS_MIN (
        .alarm_time(alarm_time_ms_min),
        .current_time(current_time_ms_min),
        .show_alarm(show_a),
        .show_new_time(show_current_time),
        .key(key_ms_min),
        .display_time(display_ms_min),
        .sound_alarm(sound_alarm3)
    );

    lcd_driver LS_MIN (
        .alarm_time(alarm_time_ls_min),
        .current_time(current_time_ls_min),
        .show_alarm(show_a),
        .show_new_time(show_current_time),
        .key(key_ls_min),
        .display_time(display_ls_min),
        .sound_alarm(sound_alarm4)
    );

    assign sound_a = sound_alarm1 & sound_alarm2 & sound_alarm3 & sound_alarm4;

endmodule

fsm.v
`timescale 1ns/1ps
module fsm (
    input  wire       clock,
    input  wire       reset,
    input  wire       one_second,
    input  wire       time_button,
    input  wire       alarm_button,
    input  wire [3:0] key,
    output reg        reset_count,
    output reg        load_new_a,
    output reg        show_a,
    output reg        show_new_time,
    output reg        load_new_c,
    output reg        shift
);

    reg [2:0] pre_state, next_state;
    wire time_out;
    reg [3:0] count1, count2;

    parameter SHOW_TIME        = 3'b000;
    parameter KEY_ENTRY        = 3'b001;
    parameter KEY_STORED       = 3'b010;
    parameter SHOW_ALARM       = 3'b011;
    parameter SET_ALARM_TIME   = 3'b100;
    parameter SET_CURRENT_TIME = 3'b101;
    parameter KEY_WAITED       = 3'b110;
    parameter NOKEY            = 4'd10;

    always @(posedge clock or posedge reset) begin
        if (reset)
            count1 <= 4'd0;
        else if (pre_state != KEY_ENTRY)
            count1 <= 4'd0;
        else if (one_second) begin
            if (count1 == 4'd9)
                count1 <= 4'd0;
            else
                count1 <= count1 + 4'd1;
        end
    end

    always @(posedge clock or posedge reset) begin
        if (reset)
            count2 <= 4'd0;
        else if (pre_state != KEY_WAITED)
            count2 <= 4'd0;
        else if (one_second) begin
            if (count2 == 4'd9)
                count2 <= 4'd0;
            else
                count2 <= count2 + 4'd1;
        end
    end

    assign time_out = ((pre_state == KEY_ENTRY)  && (count1 == 4'd9)) ||
                      ((pre_state == KEY_WAITED) && (count2 == 4'd9));

    always @(posedge clock or posedge reset) begin
        if (reset)
            pre_state <= SHOW_TIME;
        else
            pre_state <= next_state;
    end

    always @(*) begin
        case (pre_state)
            SHOW_TIME: begin
                if (alarm_button)
                    next_state = SHOW_ALARM;
                else if (key != NOKEY)
                    next_state = KEY_STORED;
                else
                    next_state = SHOW_TIME;
            end

            KEY_STORED: begin
                next_state = KEY_WAITED;
            end

            KEY_WAITED: begin
                if (key == NOKEY)
                    next_state = KEY_ENTRY;
                else if (time_out)
                    next_state = SHOW_TIME;
                else
                    next_state = KEY_WAITED;
            end

            KEY_ENTRY: begin
                if (alarm_button)
                    next_state = SET_ALARM_TIME;
                else if (time_button)
                    next_state = SET_CURRENT_TIME;
                else if (time_out)
                    next_state = SHOW_TIME;
                else if (key != NOKEY)
                    next_state = KEY_STORED;
                else
                    next_state = KEY_ENTRY;
            end

            SHOW_ALARM: begin
                if (alarm_button)
                    next_state = SHOW_ALARM;
                else
                    next_state = SHOW_TIME;
            end

            SET_ALARM_TIME:   next_state = SHOW_TIME;
            SET_CURRENT_TIME: next_state = SHOW_TIME;
            default:          next_state = SHOW_TIME;
        endcase
    end

    always @(*) begin
        reset_count   = 1'b0;
        load_new_a    = 1'b0;
        show_a        = 1'b0;
        show_new_time = 1'b0;
        load_new_c    = 1'b0;
        shift         = 1'b0;

        case (pre_state)
            KEY_ENTRY: begin
                show_new_time = 1'b1;
            end

            KEY_STORED: begin
                show_new_time = 1'b1;
                shift         = 1'b1;
            end

            KEY_WAITED: begin
                show_new_time = 1'b1;
            end

            SHOW_ALARM: begin
                show_a = 1'b1;
            end

            SET_ALARM_TIME: begin
                load_new_a = 1'b1;
            end

            SET_CURRENT_TIME: begin
                load_new_c  = 1'b1;
                reset_count = 1'b1;
            end
        endcase
    end
endmodule

keyreg.v
`timescale 1ns/1ps
module keyreg (
    input  wire       reset,
    input  wire       clock,
    input  wire       shift,
    input  wire [3:0] key,
    output reg  [3:0] key_buffer_ls_min,
    output reg  [3:0] key_buffer_ms_min,
    output reg  [3:0] key_buffer_ls_hr,
    output reg  [3:0] key_buffer_ms_hr
);

    always @(posedge clock or posedge reset) begin
        if (reset) begin
            key_buffer_ms_hr  <= 4'd0;
            key_buffer_ls_hr  <= 4'd0;
            key_buffer_ms_min <= 4'd0;
            key_buffer_ls_min <= 4'd0;
        end else if (shift) begin
            key_buffer_ms_hr  <= key_buffer_ls_hr;
            key_buffer_ls_hr  <= key_buffer_ms_min;
            key_buffer_ms_min <= key_buffer_ls_min;
            key_buffer_ls_min <= key;
        end
    end
endmodule

alarm_reg.v
`timescale 1ns/1ps
module alarm_reg (
    input  wire [3:0] new_alarm_ms_hr,
    input  wire [3:0] new_alarm_ls_hr,
    input  wire [3:0] new_alarm_ms_min,
    input  wire [3:0] new_alarm_ls_min,
    input  wire       load_new_alarm,
    input  wire       clock,
    input  wire       reset,
    output reg  [3:0] alarm_time_ms_hr,
    output reg  [3:0] alarm_time_ls_hr,
    output reg  [3:0] alarm_time_ms_min,
    output reg  [3:0] alarm_time_ls_min
);

    always @(posedge clock or posedge reset) begin
        if (reset) begin
            alarm_time_ms_hr  <= 4'd0;
            alarm_time_ls_hr  <= 4'd0;
            alarm_time_ms_min <= 4'd0;
            alarm_time_ls_min <= 4'd0;
        end else if (load_new_alarm) begin
            alarm_time_ms_hr  <= new_alarm_ms_hr;
            alarm_time_ls_hr  <= new_alarm_ls_hr;
            alarm_time_ms_min <= new_alarm_ms_min;
            alarm_time_ls_min <= new_alarm_ls_min;
        end
    end
endmodule

counter.v
`timescale 1ns/1ps
module counter (
    input  wire       clk,
    input  wire       reset,
    input  wire       one_minute,
    input  wire       load_new_c,
    input  wire [3:0] new_current_time_ms_hr,
    input  wire [3:0] new_current_time_ms_min,
    input  wire [3:0] new_current_time_ls_hr,
    input  wire [3:0] new_current_time_ls_min,
    output reg  [3:0] current_time_ms_hr,
    output reg  [3:0] current_time_ms_min,
    output reg  [3:0] current_time_ls_hr,
    output reg  [3:0] current_time_ls_min
);

    always @(posedge clk or posedge reset) begin
        if (reset) begin
            current_time_ms_hr  <= 4'd0;
            current_time_ms_min <= 4'd0;
            current_time_ls_hr  <= 4'd0;
            current_time_ls_min <= 4'd0;
        end else if (load_new_c) begin
            current_time_ms_hr  <= new_current_time_ms_hr;
            current_time_ms_min <= new_current_time_ms_min;
            current_time_ls_hr  <= new_current_time_ls_hr;
            current_time_ls_min <= new_current_time_ls_min;
        end else if (one_minute) begin
            if (current_time_ms_hr == 4'd2 &&
                current_time_ls_hr == 4'd3 &&
                current_time_ms_min == 4'd5 &&
                current_time_ls_min == 4'd9) begin
                current_time_ms_hr  <= 4'd0;
                current_time_ls_hr  <= 4'd0;
                current_time_ms_min <= 4'd0;
                current_time_ls_min <= 4'd0;
            end else if (current_time_ms_hr == 4'd0 &&
                         current_time_ls_hr == 4'd9 &&
                         current_time_ms_min == 4'd5 &&
                         current_time_ls_min == 4'd9) begin
                current_time_ms_hr  <= 4'd1;
                current_time_ls_hr  <= 4'd0;
                current_time_ms_min <= 4'd0;
                current_time_ls_min <= 4'd0;
            end else if (current_time_ms_min == 4'd5 &&
                         current_time_ls_min == 4'd9) begin
                if (current_time_ls_hr == 4'd9) begin
                    current_time_ms_hr <= current_time_ms_hr + 4'd1;
                    current_time_ls_hr <= 4'd0;
                end else begin
                    current_time_ls_hr <= current_time_ls_hr + 4'd1;
                end
                current_time_ms_min <= 4'd0;
                current_time_ls_min <= 4'd0;
            end else if (current_time_ls_min == 4'd9) begin
                current_time_ms_min <= current_time_ms_min + 4'd1;
                current_time_ls_min <= 4'd0;
            end else begin
                current_time_ls_min <= current_time_ls_min + 4'd1;
            end
        end
    end
endmodule

timing_generator.v
`timescale 1ns/1ps
module timing_generator (
    input  wire       clock,
    input  wire       reset,
    input  wire       fastwatch,
    input  wire       reset_count,
    output reg        one_second
);
    reg [31:0] count;
    reg [31:0] limit;

    always @(*) begin
        if (fastwatch)
            limit = 32'd256;
        else
            limit = 32'd50000000;
    end

    always @(posedge clock or posedge reset) begin
        if (reset) begin
            count      <= 32'd0;
            one_second <= 1'b0;
        end else if (reset_count) begin
            count      <= 32'd0;
            one_second <= 1'b0;
        end else if (count == (limit - 1)) begin
            count      <= 32'd0;
            one_second <= 1'b1;
        end else begin
            count      <= count + 32'd1;
            one_second <= 1'b0;
        end
    end
endmodule

alarm_clock_top.v
`timescale 1ns/1ps
module alarm_clock_top (
    input  wire       clock,
    input  wire [3:0] key,
    input  wire       reset,
    input  wire       time_button,
    input  wire       alarm_button,
    input  wire       fastwatch,
    output wire [7:0] ms_hour,
    output wire [7:0] ls_hour,
    output wire [7:0] ms_minute,
    output wire [7:0] ls_minute,
    output wire       alarm_sound
);

    wire one_second;
    wire reset_count;
    wire load_new_a, show_a, show_new_time, load_new_c, shift;

    wire [3:0] current_time_ms_hr, current_time_ls_hr, current_time_ms_min, current_time_ls_min;
    wire [3:0] alarm_time_ms_hr, alarm_time_ls_hr, alarm_time_ms_min, alarm_time_ls_min;
    wire [3:0] key_ms_hr, key_ls_hr, key_ms_min, key_ls_min;

    timing_generator TG (
        .clock(clock),
        .reset(reset),
        .fastwatch(fastwatch),
        .reset_count(reset_count),
        .one_second(one_second)
    );

    counter CNT (
        .clk(clock),
        .reset(reset),
        .one_minute(one_second),
        .load_new_c(load_new_c),
        .new_current_time_ms_hr(key_ms_hr),
        .new_current_time_ms_min(key_ms_min),
        .new_current_time_ls_hr(key_ls_hr),
        .new_current_time_ls_min(key_ls_min),
        .current_time_ms_hr(current_time_ms_hr),
        .current_time_ms_min(current_time_ms_min),
        .current_time_ls_hr(current_time_ls_hr),
        .current_time_ls_min(current_time_ls_min)
    );

    alarm_reg ALARM (
        .new_alarm_ms_hr(key_ms_hr),
        .new_alarm_ls_hr(key_ls_hr),
        .new_alarm_ms_min(key_ms_min),
        .new_alarm_ls_min(key_ls_min),
        .load_new_alarm(load_new_a),
        .clock(clock),
        .reset(reset),
        .alarm_time_ms_hr(alarm_time_ms_hr),
        .alarm_time_ls_hr(alarm_time_ls_hr),
        .alarm_time_ms_min(alarm_time_ms_min),
        .alarm_time_ls_min(alarm_time_ls_min)
    );

    keyreg KEYREG (
        .reset(reset),
        .clock(clock),
        .shift(shift),
        .key(key),
        .key_buffer_ls_min(key_ls_min),
        .key_buffer_ms_min(key_ms_min),
        .key_buffer_ls_hr(key_ls_hr),
        .key_buffer_ms_hr(key_ms_hr)
    );

    fsm FSM (
        .clock(clock),
        .reset(reset),
        .one_second(one_second),
        .time_button(time_button),
        .alarm_button(alarm_button),
        .key(key),
        .reset_count(reset_count),
        .load_new_a(load_new_a),
        .show_a(show_a),
        .show_new_time(show_new_time),
        .load_new_c(load_new_c),
        .shift(shift)
    );

    lcd_driver_4 LCD (
        .alarm_time_ms_hr(alarm_time_ms_hr),
        .alarm_time_ls_hr(alarm_time_ls_hr),
        .alarm_time_ms_min(alarm_time_ms_min),
        .alarm_time_ls_min(alarm_time_ls_min),
        .current_time_ms_hr(current_time_ms_hr),
        .current_time_ls_hr(current_time_ls_hr),
        .current_time_ms_min(current_time_ms_min),
        .current_time_ls_min(current_time_ls_min),
        .key_ms_hr(key_ms_hr),
        .key_ls_hr(key_ls_hr),
        .key_ms_min(key_ms_min),
        .key_ls_min(key_ls_min),
        .show_a(show_a),
        .show_current_time(show_new_time),
        .display_ms_hr(ms_hour),
        .display_ls_hr(ls_hour),
        .display_ms_min(ms_minute),
        .display_ls_min(ls_minute),
        .sound_a(alarm_sound)
    );

endmodule

tb_alarm_clock.v
`timescale 1ns/1ps
module tb_alarm_clock;

    reg clk;
    reg reset;
    reg fast_watch;
    reg alarm_button;
    reg time_button;
    reg [3:0] key;

    wire [7:0] display_ms_hr;
    wire [7:0] display_ls_hr;
    wire [7:0] display_ms_min;
    wire [7:0] display_ls_min;
    wire sound_alarm;

    parameter cycle = 2;

    alarm_clock_top DUV (
        .clock(clk),
        .key(key),
        .reset(reset),
        .time_button(time_button),
        .alarm_button(alarm_button),
        .fastwatch(fast_watch),
        .ms_hour(display_ms_hr),
        .ls_hour(display_ls_hr),
        .ms_minute(display_ms_min),
        .ls_minute(display_ls_min),
        .alarm_sound(sound_alarm)
    );

    initial begin
        clk = 1'b0;
        forever #(cycle/2) clk = ~clk;
    end

    initial begin
        $dumpfile("alarm_clock.vcd");
        $dumpvars(0, tb_alarm_clock);

        reset = 1'b1;
        fast_watch = 1'b0;
        alarm_button = 1'b0;
        time_button = 1'b0;
        key = 4'd10;

        #10;
        reset = 1'b0;
        fast_watch = 1'b1;

        // set current time = 11:23
        key = 4'd1; repeat (3) @(negedge clk);
        key = 4'd10; @(negedge clk);
        key = 4'd1; repeat (3) @(negedge clk);
        key = 4'd10; @(negedge clk);
        key = 4'd2; repeat (3) @(negedge clk);
        key = 4'd10; @(negedge clk);
        key = 4'd3; repeat (3) @(negedge clk);
        key = 4'd10; @(negedge clk);
        time_button = 1'b1; @(negedge clk); time_button = 1'b0;

        // set alarm time = 11:30
        key = 4'd1; repeat (3) @(negedge clk);
        key = 4'd10; @(negedge clk);
        key = 4'd1; repeat (3) @(negedge clk);
        key = 4'd10; @(negedge clk);
        key = 4'd3; repeat (3) @(negedge clk);
        key = 4'd10; @(negedge clk);
        key = 4'd0; repeat (3) @(negedge clk);
        key = 4'd10; @(negedge clk);
        alarm_button = 1'b1; @(negedge clk); alarm_button = 1'b0;

        // wait for alarm match
        #(7*256*2);
        repeat (4*2564) @(negedge clk);
        $finish;
    end

    initial begin
        $monitor("%0t ns  MS_HR=%h LS_HR=%h MS_MIN=%h LS_MIN=%h  ALARM=%b",
                 $time,
                 display_ms_hr[3:0],
                 display_ls_hr[3:0],
                 display_ms_min[3:0],
                 display_ls_min[3:0],
                 sound_alarm);
    end
endmodule

alarm_clock.vcd
$date
	Mon May 25 18:41:03 2026
$end
$version
	Icarus Verilog
$end
$timescale
	1ps
$end
$scope module tb_alarm_clock $end
$var wire 8 ! display_ls_hr [7:0] $end
$var wire 8 " display_ls_min [7:0] $end
$var wire 8 # display_ms_hr [7:0] $end
$var wire 8 $ display_ms_min [7:0] $end
$var wire 1 % sound_alarm $end
$var reg 1 & alarm_button $end
$var reg 1 ' clk $end
$var reg 1 ( fast_watch $end
$var reg 4 ) key [3:0] $end
$var reg 1 * reset $end
$var reg 1 + time_button $end
$scope module DUV $end
$var wire 1 , alarm_button $end
$var wire 1 % alarm_sound $end
$var wire 4 - alarm_time_ls_hr [3:0] $end
$var wire 4 . alarm_time_ls_min [3:0] $end
$var wire 4 / alarm_time_ms_hr [3:0] $end
$var wire 4 0 alarm_time_ms_min [3:0] $end
$var wire 1 1 clock $end
$var wire 4 2 current_time_ls_hr [3:0] $end
$var wire 4 3 current_time_ls_min [3:0] $end
$var wire 4 4 current_time_ms_hr [3:0] $end
$var wire 4 5 current_time_ms_min [3:0] $end
$var wire 1 6 fastwatch $end
$var wire 4 7 key [3:0] $end
$var wire 4 8 key_ls_hr [3:0] $end
$var wire 4 9 key_ls_min [3:0] $end
$var wire 4 : key_ms_hr [3:0] $end
$var wire 4 ; key_ms_min [3:0] $end
$var wire 1 < load_new_a $end
$var wire 1 = load_new_c $end
$var wire 8 > ls_hour [7:0] $end
$var wire 8 ? ls_minute [7:0] $end
$var wire 8 @ ms_hour [7:0] $end
$var wire 8 A ms_minute [7:0] $end
$var wire 1 B one_second $end
$var wire 1 C reset $end
$var wire 1 D reset_count $end
$var wire 1 E shift $end
$var wire 1 F show_a $end
$var wire 1 G show_new_time $end
$var wire 1 H time_button $end
$scope module TG $end
$var wire 1 1 clock $end
$var wire 1 6 fastwatch $end
$var wire 1 C reset $end
$var wire 1 D reset_count $end
$var reg 32 I count [31:0] $end
$var reg 32 J limit [31:0] $end
$var reg 1 K one_second $end
$upscope $end
$scope module CNT $end
$var wire 1 1 clk $end
$var wire 1 = load_new_c $end
$var wire 4 L new_current_time_ls_hr [3:0] $end
$var wire 4 M new_current_time_ls_min [3:0] $end
$var wire 4 N new_current_time_ms_hr [3:0] $end
$var wire 4 O new_current_time_ms_min [3:0] $end
$var wire 1 B one_minute $end
$var wire 1 C reset $end
$var reg 4 P current_time_ls_hr [3:0] $end
$var reg 4 Q current_time_ls_min [3:0] $end
$var reg 4 R current_time_ms_hr [3:0] $end
$var reg 4 S current_time_ms_min [3:0] $end
$upscope $end
$scope module ALARM $end
$var wire 1 1 clock $end
$var wire 1 < load_new_alarm $end
$var wire 4 T new_alarm_ls_hr [3:0] $end
$var wire 4 U new_alarm_ls_min [3:0] $end
$var wire 4 V new_alarm_ms_hr [3:0] $end
$var wire 4 W new_alarm_ms_min [3:0] $end
$var wire 1 C reset $end
$var reg 4 X alarm_time_ls_hr [3:0] $end
$var reg 4 Y alarm_time_ls_min [3:0] $end
$var reg 4 Z alarm_time_ms_hr [3:0] $end
$var reg 4 [ alarm_time_ms_min [3:0] $end
$upscope $end
$scope module KEYREG $end
$var wire 1 1 clock $end
$var wire 4 \ key [3:0] $end
$var wire 1 C reset $end
$var wire 1 E shift $end
$var reg 4 ] key_buffer_ls_hr [3:0] $end
$var reg 4 ^ key_buffer_ls_min [3:0] $end
$var reg 4 _ key_buffer_ms_hr [3:0] $end
$var reg 4 ` key_buffer_ms_min [3:0] $end
$upscope $end
$scope module FSM $end
$var wire 1 , alarm_button $end
$var wire 1 1 clock $end
$var wire 4 a key [3:0] $end
$var wire 1 B one_second $end
$var wire 1 C reset $end
$var wire 1 H time_button $end
$var wire 1 b time_out $end
$var reg 4 c count1 [3:0] $end
$var reg 4 d count2 [3:0] $end
$var reg 1 e load_new_a $end
$var reg 1 f load_new_c $end
$var reg 3 g next_state [2:0] $end
$var reg 3 h pre_state [2:0] $end
$var reg 1 i reset_count $end
$var reg 1 j shift $end
$var reg 1 k show_a $end
$var reg 1 l show_new_time $end
$upscope $end
$scope module LCD $end
$var wire 4 m alarm_time_ls_hr [3:0] $end
$var wire 4 n alarm_time_ls_min [3:0] $end
$var wire 4 o alarm_time_ms_hr [3:0] $end
$var wire 4 p alarm_time_ms_min [3:0] $end
$var wire 4 q current_time_ls_hr [3:0] $end
$var wire 4 r current_time_ls_min [3:0] $end
$var wire 4 s current_time_ms_hr [3:0] $end
$var wire 4 t current_time_ms_min [3:0] $end
$var wire 8 u display_ls_hr [7:0] $end
$var wire 8 v display_ls_min [7:0] $end
$var wire 8 w display_ms_hr [7:0] $end
$var wire 8 x display_ms_min [7:0] $end
$var wire 4 y key_ls_hr [3:0] $end
$var wire 4 z key_ls_min [3:0] $end
$var wire 4 { key_ms_hr [3:0] $end
$var wire 4 | key_ms_min [3:0] $end
$var wire 1 F show_a $end
$var wire 1 G show_current_time $end
$var wire 1 % sound_a $end
$var wire 1 } sound_alarm1 $end
$var wire 1 ~ sound_alarm2 $end
$var wire 1 !" sound_alarm3 $end
$var wire 1 "" sound_alarm4 $end
$scope module MS_HR $end
$var wire 4 #" alarm_time [3:0] $end
$var wire 4 $" current_time [3:0] $end
$var wire 4 %" key [3:0] $end
$var wire 1 F show_alarm $end
$var wire 1 G show_new_time $end
$var reg 8 &" display_time [7:0] $end
$var reg 4 '" display_value [3:0] $end
$var reg 1 (" sound_alarm $end
$upscope $end
$scope module LS_HR $end
$var wire 4 )" alarm_time [3:0] $end
$var wire 4 *" current_time [3:0] $end
$var wire 4 +" key [3:0] $end
$var wire 1 F show_alarm $end
$var wire 1 G show_new_time $end
$var reg 8 ," display_time [7:0] $end
$var reg 4 -" display_value [3:0] $end
$var reg 1 ." sound_alarm $end
$upscope $end
$scope module MS_MIN $end
$var wire 4 /" alarm_time [3:0] $end
$var wire 4 0" current_time [3:0] $end
$var wire 4 1" key [3:0] $end
$var wire 1 F show_alarm $end
$var wire 1 G show_new_time $end
$var reg 8 2" display_time [7:0] $end
$var reg 4 3" display_value [3:0] $end
$var reg 1 4" sound_alarm $end
$upscope $end
$scope module LS_MIN $end
$var wire 4 5" alarm_time [3:0] $end
$var wire 4 6" current_time [3:0] $end
$var wire 4 7" key [3:0] $end
$var wire 1 F show_alarm $end
$var wire 1 G show_new_time $end
$var reg 8 8" display_time [7:0] $end
$var reg 4 9" display_value [3:0] $end
$var reg 1 :" sound_alarm $end
$upscope $end
$upscope $end
$upscope $end
$upscope $end
$enddefinitions $end
#0
$dumpvars
1:"
b0 9"
b110000 8"
b0 7"
b0 6"
b0 5"
14"
b0 3"
b110000 2"
b0 1"
b0 0"
b0 /"
1."
b0 -"
b110000 ,"
b0 +"
b0 *"
b0 )"
1("
b0 '"
b110000 &"
b0 %"
b0 $"
b0 #"
1""
1!"
1~
1}
b0 |
b0 {
b0 z
b0 y
b110000 x
b110000 w
b110000 v
b110000 u
b0 t
b0 s
b0 r
b0 q
b0 p
b0 o
b0 n
b0 m
0l
0k
0j
0i
b0 h
b0 g
0f
0e
b0 d
b0 c
0b
b1010 a
b0 `
b0 _
b0 ^
b0 ]
b1010 \
b0 [
b0 Z
b0 Y
b0 X
b0 W
b0 V
b0 U
b0 T
b0 S
b0 R
b0 Q
b0 P
b0 O
b0 N
b0 M
b0 L
0K
b10111110101111000010000000 J
b0 I
0H
0G
0F
0E
0D
1C
0B
b110000 A
b110000 @
b110000 ?
b110000 >
0=
0<
b0 ;
b0 :
b0 9
b0 8
b1010 7
06
b0 5
b0 4
b0 3
b0 2
01
b0 0
b0 /
b0 .
b0 -
0,
0+
1*
b1010 )
0(
0'
0&
1%
b110000 $
b110000 #
b110000 "
b110000 !
$end
#1000
1'
11
#2000
0'
01
#3000
1'
11
#4000
0'
01
#5000
1'
11
#6000
0'
01
#7000
1'
11
#8000
0'
01
#9000
1'
11
#10000
b10 g
b100000000 J
0'
01
b1 )
b1 7
b1 \
b1 a
1(
16
0*
0C
#11000
1j
1E
1l
1G
b110 g
b1 I
b10 h
1'
11
#12000
0'
01
#13000
b110001 8"
b110001 "
b110001 ?
b110001 v
0j
0E
1l
1G
b1 9"
b110 h
b1 ^
b1 9
b1 M
b1 U
b1 z
b1 7"
b10 I
1'
11
#14000
b1 g
b1010 )
b1010 7
b1010 \
b1010 a
0'
01
#15000
1l
1G
b11 I
b1 h
1'
11
#16000
b10 g
b1 )
b1 7
b1 \
b1 a
0'
01
#17000
1j
1E
1l
1G
b110 g
b10 h
b100 I
1'
11
#18000
0'
01
#19000
b110001 2"
b110001 $
b110001 A
b110001 x
b1 3"
0j
0E
1l
1G
b101 I
b1 `
b1 ;
b1 O
b1 W
b1 |
b1 1"
b110 h
1'
11
#20000
0'
01
#21000
b110 I
1'
11
#22000
b1 g
b1010 )
b1010 7
b1010 \
b1010 a
0'
01
#23000
1l
1G
b111 I
b1 h
1'
11
#24000
b10 g
b10 )
b10 7
b10 \
b10 a
0'
01
#25000
1j
1E
1l
1G
b110 g
b10 h
b1000 I
1'
11
#26000
0'
01
#27000
b110010 8"
b110010 "
b110010 ?
b110010 v
b110001 ,"
b110001 !
b110001 >
b110001 u
b10 9"
b1 -"
0j
0E
1l
1G
b1001 I
b10 ^
b10 9
b10 M
b10 U
b10 z
b10 7"
b1 ]
b1 8
b1 L
b1 T
b1 y
b1 +"
b110 h
1'
11
#28000
0'
01
#29000
b1010 I
1'
11
#30000
b1 g
b1010 )
b1010 7
b1010 \
b1010 a
0'
01
#31000
1l
1G
b1011 I
b1 h
1'
11
#32000
b10 g
b11 )
b11 7
b11 \
b11 a
0'
01
#33000
1j
1E
1l
1G
b110 g
b10 h
b1100 I
1'
11
#34000
0'
01
#35000
b110011 8"
b110011 "
b110011 ?
b110011 v
b110010 2"
b110010 $
b110010 A
b110010 x
b110001 &"
b110001 #
b110001 @
b110001 w
b11 9"
b10 3"
b1 '"
0j
0E
1l
1G
b1101 I
b11 ^
b11 9
b11 M
b11 U
b11 z
b11 7"
b10 `
b10 ;
b10 O
b10 W
b10 |
b10 1"
b1 _
b1 :
b1 N
b1 V
b1 {
b1 %"
b110 h
1'
11
#36000
0'
01
#37000
b1110 I
1'
11
#38000
b1 g
b1010 )
b1010 7
b1010 \
b1010 a
0'
01
#39000
1l
1G
b1111 I
b1 h
1'
11
#40000
b101 g
1+
1H
0'
01
#41000
b110000 8"
b110000 "
b110000 ?
b110000 v
b110000 2"
b110000 $
b110000 A
b110000 x
b110000 ,"
b110000 !
b110000 >
b110000 u
b110000 &"
b110000 #
b110000 @
b110000 w
b0 9"
b0 3"
b0 -"
b0 '"
1i
1D
1f
1=
0l
0G
b0 g
b101 h
b10000 I
1'
11
#42000
b1 )
b1 7
b1 \
b1 a
0+
0H
0'
01
#43000
0%
b110011 8"
b110011 "
b110011 ?
b110011 v
b110001 ,"
b110001 !
b110001 >
b110001 u
b110010 2"
b110010 $
b110010 A
b110010 x
b110001 &"
b110001 #
b110001 @
b110001 w
0:"
0""
b11 9"
0."
0~
b1 -"
04"
0!"
b10 3"
0("
0}
b1 '"
0f
0=
0i
0D
b10 g
b0 I
b11 Q
b11 3
b11 r
b11 6"
b1 P
b1 2
b1 q
b1 *"
b10 S
b10 5
b10 t
b10 0"
b1 R
b1 4
b1 s
b1 $"
b0 h
1'
11
#44000
0'
01
#45000
1j
1E
1l
1G
b110 g
b10 h
b1 I
1'
11
#46000
0'
01
#47000
b110001 8"
b110001 "
b110001 ?
b110001 v
b110011 2"
b110011 $
b110011 A
b110011 x
b110010 ,"
b110010 !
b110010 >
b110010 u
b1 9"
b11 3"
b10 -"
0j
0E
1l
1G
b10 I
b1 ^
b1 9
b1 M
b1 U
b1 z
b1 7"
b11 `
b11 ;
b11 O
b11 W
b11 |
b11 1"
b10 ]
b10 8
b10 L
b10 T
b10 y
b10 +"
b110 h
1'
11
#48000
b1 g
b1010 )
b1010 7
b1010 \
b1010 a
0'
01
#49000
1l
1G
b1 h
b11 I
1'
11
#50000
b10 g
b1 )
b1 7
b1 \
b1 a
0'
01
#51000
1j
1E
1l
1G
b110 g
b100 I
b10 h
1'
11
#52000
0'
01
#53000
b110001 2"
b110001 $
b110001 A
b110001 x
b110011 ,"
b110011 !
b110011 >
b110011 u
b110010 &"
b110010 #
b110010 @
b110010 w
0j
0E
1l
1G
b1 3"
b11 -"
b10 '"
b110 h
b1 `
b1 ;
b1 O
b1 W
b1 |
b1 1"
b11 ]
b11 8
b11 L
b11 T
b11 y
b11 +"
b10 _
b10 :
b10 N
b10 V
b10 {
b10 %"
b101 I
1'
11
#54000
0'
01
#55000
b110 I
1'
11
#56000
b1 g
b1010 )
b1010 7
b1010 \
b1010 a
0'
01
#57000
1l
1G
b1 h
b111 I
1'
11
#58000
b10 g
b11 )
b11 7
b11 \
b11 a
0'
01
#59000
1j
1E
1l
1G
b110 g
b1000 I
b10 h
1'
11
#60000
0'
01
#61000
b110011 8"
b110011 "
b110011 ?
b110011 v
b110001 ,"
b110001 !
b110001 >
b110001 u
b110011 &"
b110011 #
b110011 @
b110011 w
0j
0E
1l
1G
b11 9"
b1 -"
b11 '"
b110 h
b11 ^
b11 9
b11 M
b11 U
b11 z
b11 7"
b1 ]
b1 8
b1 L
b1 T
b1 y
b1 +"
b11 _
b11 :
b11 N
b11 V
b11 {
b11 %"
b1001 I
1'
11
#62000
0'
01
